{"nodes": [{"id": "src_utils_formatbibletext_ts", "label": "formatBibleText.ts", "file_type": "code", "source_file": "src/utils/formatBibleText.ts", "source_location": "L1"}, {"id": "formatbibletext_formatbibletext", "label": "formatBibleText()", "file_type": "code", "source_file": "src/utils/formatBibleText.ts", "source_location": "L5"}], "edges": [{"source": "src_utils_formatbibletext_ts", "target": "chaptercounts", "relation": "imports_from", "confidence": "EXTRACTED", "source_file": "src/utils/formatBibleText.ts", "source_location": "L1", "weight": 1.0}, {"source": "src_utils_formatbibletext_ts", "target": "types", "relation": "imports_from", "confidence": "EXTRACTED", "source_file": "src/utils/formatBibleText.ts", "source_location": "L2", "weight": 1.0}, {"source": "src_utils_formatbibletext_ts", "target": "biblebooks", "relation": "imports_from", "confidence": "EXTRACTED", "source_file": "src/utils/formatBibleText.ts", "source_location": "L3", "weight": 1.0}, {"source": "src_utils_formatbibletext_ts", "target": "formatbibletext_formatbibletext", "relation": "contains", "confidence": "EXTRACTED", "source_file": "src/utils/formatBibleText.ts", "source_location": "L5", "weight": 1.0}], "raw_calls": [{"caller_nid": "formatbibletext_formatbibletext", "callee": "getBibleBookById", "source_file": "src/utils/formatBibleText.ts", "source_location": "L10"}, {"caller_nid": "formatbibletext_formatbibletext", "callee": "map", "source_file": "src/utils/formatBibleText.ts", "source_location": "L19"}, {"caller_nid": "formatbibletext_formatbibletext", "callee": "includes", "source_file": "src/utils/formatBibleText.ts", "source_location": "L24"}, {"caller_nid": "formatbibletext_formatbibletext", "callee": "join", "source_file": "src/utils/formatBibleText.ts", "source_location": "L26"}, {"caller_nid": "formatbibletext_formatbibletext", "callee": "join", "source_file": "src/utils/formatBibleText.ts", "source_location": "L37"}]}